include/nanoarrow/nanoarrow.h
include/nanoarrow/nanoarrow.hpp
include/nanoarrow/nanoarrow_config.h
include/nanoarrow/common/inline_array.h
include/nanoarrow/common/inline_buffer.h
include/nanoarrow/common/inline_types.h
lib/libnanoarrow.a
lib64/cmake/nanoarrow/nanoarrow-config-version.cmake
lib64/cmake/nanoarrow/nanoarrow-config.cmake
lib64/cmake/nanoarrow/nanoarrow-targets-release.cmake
lib64/cmake/nanoarrow/nanoarrow-targets.cmake
pylibcudf/CMakeLists.txt
pylibcudf/GIT_COMMIT
pylibcudf/VERSION
pylibcudf/__init__.pxd
pylibcudf/__init__.py
pylibcudf/_interop_helpers.cpython-311-x86_64-linux-gnu.so
pylibcudf/_interop_helpers.pxd
pylibcudf/_interop_helpers.pyx
pylibcudf/_version.py
pylibcudf/aggregation.cpython-311-x86_64-linux-gnu.so
pylibcudf/aggregation.pxd
pylibcudf/aggregation.pyi
pylibcudf/aggregation.pyx
pylibcudf/binaryop.cpython-311-x86_64-linux-gnu.so
pylibcudf/binaryop.pxd
pylibcudf/binaryop.pyi
pylibcudf/binaryop.pyx
pylibcudf/column.cpython-311-x86_64-linux-gnu.so
pylibcudf/column.pxd
pylibcudf/column.pyi
pylibcudf/column.pyx
pylibcudf/column_factories.cpython-311-x86_64-linux-gnu.so
pylibcudf/column_factories.pxd
pylibcudf/column_factories.pyi
pylibcudf/column_factories.pyx
pylibcudf/concatenate.cpython-311-x86_64-linux-gnu.so
pylibcudf/concatenate.pxd
pylibcudf/concatenate.pyi
pylibcudf/concatenate.pyx
pylibcudf/contiguous_split.cpython-311-x86_64-linux-gnu.so
pylibcudf/contiguous_split.pxd
pylibcudf/contiguous_split.pyi
pylibcudf/contiguous_split.pyx
pylibcudf/copying.cpython-311-x86_64-linux-gnu.so
pylibcudf/copying.pxd
pylibcudf/copying.pyi
pylibcudf/copying.pyx
pylibcudf/datetime.cpython-311-x86_64-linux-gnu.so
pylibcudf/datetime.pxd
pylibcudf/datetime.pyi
pylibcudf/datetime.pyx
pylibcudf/exception_handler.pxd
pylibcudf/expressions.cpython-311-x86_64-linux-gnu.so
pylibcudf/expressions.pxd
pylibcudf/expressions.pyi
pylibcudf/expressions.pyx
pylibcudf/filling.cpython-311-x86_64-linux-gnu.so
pylibcudf_cu13-25.12.0.dist-info/METADATA
pylibcudf_cu13-25.12.0.dist-info/WHEEL
pylibcudf_cu13-25.12.0.dist-info/RECORD
pylibcudf_cu13-25.12.0.dist-info/licenses/LICENSE
